mkdocs_exclude_unused/__init__.py
mkdocs_exclude_unused/plugin.py
mkdocs_exclude_unused-1.0.1.dist-info/LICENSE
mkdocs_exclude_unused-1.0.1.dist-info/METADATA
mkdocs_exclude_unused-1.0.1.dist-info/WHEEL
mkdocs_exclude_unused-1.0.1.dist-info/entry_points.txt
mkdocs_exclude_unused-1.0.1.dist-info/top_level.txt
mkdocs_exclude_unused-1.0.1.dist-info/RECORD
