Metadata-Version: 2.1
Name: mkdocs-exclude-unused
Version: 1.0.1
Summary: Simple plugin to exclude notused .md files from docs folder
Home-page: https://github.com/michal2612/mkdocs-exclude-unused
Author: Michal Domanski
License: MIT
License-File: LICENSE
Requires-Dist: mkdocs
